TmpVar/__init__.py
TmpVar/main.py
TmpVar-0.0.1.dist-info/METADATA
TmpVar-0.0.1.dist-info/WHEEL
TmpVar-0.0.1.dist-info/top_level.txt
TmpVar-0.0.1.dist-info/RECORD
