Metadata-Version: 2.1
Name: TmpVar
Version: 0.0.1
Summary: create a temporary environment to run some code
Home-page: https://github.com/Blockhead-yj/TmpVar
Author: Blockhead-yj
Author-email: 136271877@qq.com
License: UNKNOWN
Platform: UNKNOWN
Requires-Python: >=3.6
